setup.py
span/__init__.py
span.egg-info/PKG-INFO
span.egg-info/SOURCES.txt
span.egg-info/dependency_links.txt
span.egg-info/not-zip-safe
span.egg-info/top_level.txt