Metadata-Version: 1.0
Name: span
Version: 0.0.1
Summary: Helper for determining basic relationships between datetime ranges
Home-page: https://github.com/appointlet/span
Author: Jared Morse <jared@appointlet.com>
Author-email: jared@appointlet.com
License: BSD
Keywords: span,datetime
Platform: UNKNOWN
Classifier: Programming Language :: Python
Classifier: Topic :: Software Development :: Libraries :: Python Modules
